django_db_helper/__init__.py
django_db_helper/get_object_or_none.py
django_db_helper-0.0.2.dist-info/LICENSE
django_db_helper-0.0.2.dist-info/METADATA
django_db_helper-0.0.2.dist-info/WHEEL
django_db_helper-0.0.2.dist-info/top_level.txt
django_db_helper-0.0.2.dist-info/RECORD
