Metadata-Version: 2.1
Name: django-db-helper
Version: 0.0.2
Summary: Package contain necessary tools to complement your Django ORM usage
Home-page: UNKNOWN
Author: Andrews Agyemang Opoku
Author-email: andrewsopoku6@gmail.com
License: MIT
Platform: UNKNOWN
Classifier: Intended Audience :: Developers
Classifier: License :: OSI Approved :: MIT License
Classifier: Programming Language :: Python
Classifier: Programming Language :: Python :: 3
Classifier: Programming Language :: Python :: 3.6
Classifier: Programming Language :: Python :: 3.7
Classifier: Programming Language :: Python :: 3.8
Classifier: Programming Language :: Python :: 3.9
Classifier: Operating System :: OS Independent
